model_card_toolkit/__init__.py
model_card_toolkit/base_model_card_field.py
model_card_toolkit/core.py
model_card_toolkit/core_test.py
model_card_toolkit/model_card.py
model_card_toolkit/model_card_test.py
model_card_toolkit/version.py
model_card_toolkit/documentation/__init__.py
model_card_toolkit/documentation/examples/__init__.py
model_card_toolkit/documentation/examples/cats_vs_dogs.py
model_card_toolkit/documentation/examples/cats_vs_dogs_test.py
model_card_toolkit/proto/model_card_pb2.py
model_card_toolkit/schema/v0.0.1/model_card.schema.json
model_card_toolkit/schema/v0.0.2/model_card.schema.json
model_card_toolkit/template/html/default_template.html.jinja
model_card_toolkit/template/md/default_template.md.jinja
model_card_toolkit/tfx/__init__.py
model_card_toolkit/tfx/component.py
model_card_toolkit/utils/__init__.py
model_card_toolkit/utils/graphics.py
model_card_toolkit/utils/graphics_test.py
model_card_toolkit/utils/json_util.py
model_card_toolkit/utils/json_util_test.py
model_card_toolkit/utils/source.py
model_card_toolkit/utils/tfx_util.py
model_card_toolkit/utils/tfx_util_test.py
model_card_toolkit/utils/validation.py
model_card_toolkit/utils/validation_test.py
model_card_toolkit-2.0.0.dist-info/LICENSE
model_card_toolkit-2.0.0.dist-info/METADATA
model_card_toolkit-2.0.0.dist-info/WHEEL
model_card_toolkit-2.0.0.dist-info/top_level.txt
model_card_toolkit-2.0.0.dist-info/RECORD
