Metadata-Version: 2.1
Name: model-card-toolkit
Version: 2.0.0
Summary: Model Card Toolkit
Home-page: https://github.com/tensorflow/model-card-toolkit
Author: Google LLC
Author-email: tensorflow-extended-dev@googlegroups.com
License: Apache 2.0
Keywords: model card toolkit ml metadata machine learning
Platform: UNKNOWN
Classifier: Development Status :: 4 - Beta
Classifier: Intended Audience :: Developers
Classifier: Intended Audience :: Education
Classifier: Intended Audience :: Science/Research
Classifier: License :: OSI Approved :: Apache Software License
Classifier: Operating System :: OS Independent
Classifier: Programming Language :: Python :: 3
Classifier: Programming Language :: Python :: 3.7
Classifier: Programming Language :: Python :: 3.8
Classifier: Programming Language :: Python :: 3.9
Classifier: Topic :: Scientific/Engineering
Classifier: Topic :: Scientific/Engineering :: Mathematics
Classifier: Topic :: Scientific/Engineering :: Artificial Intelligence
Classifier: Topic :: Software Development
Classifier: Topic :: Software Development :: Libraries
Classifier: Topic :: Software Development :: Libraries :: Python Modules
Requires-Python: >=3.7,<4
Requires-Dist: absl-py (<1.1,>=0.9)
Requires-Dist: jinja2 (<3.2,>=3.1)
Requires-Dist: matplotlib (<4,>=3.2.0)
Requires-Dist: jsonschema (<4,>=3.2.0)
Requires-Dist: tensorflow-data-validation (<2.0.0,>=1.5.0)
Requires-Dist: tensorflow-model-analysis (<0.42.0,>=0.36.0)
Requires-Dist: tensorflow-metadata (<2.0.0,>=1.5.0)
Requires-Dist: ml-metadata (<2.0.0,>=1.5.0)
Provides-Extra: test
Requires-Dist: pytest ; extra == 'test'
Requires-Dist: tensorflow-datasets (>=4.8.2) ; extra == 'test'
